{"inkVersion":16,"root":[{"->":"Start"},"done",{"Start":["^I shuffle into the kitchen, which is much more packed than usual, with everybody showing up for the celebatory Welcome Dinner.","\n","^The Halfway Home has these big get together dinners, whenever we get someone new, or someone leaves.","\n","^its supposed to be a big bonding moment. Or, somthing like that.","\n","^I actually barely remember my welcome dinner.","\n","end",{"#f":3}],"global decl":["ev","str","^tbd","/str",{"VAR=":"player_name"},"str","^tbd","/str",{"VAR=":"player_gender"},0,{"VAR=":"grace"},0,{"VAR=":"expression"},0,{"VAR=":"awareness"},0,{"VAR=":"fatigue"},0,{"VAR=":"stress"},0,{"VAR=":"delusion"},0,{"VAR=":"week"},"/ev","end",null],"#f":3}],"listDefs":{}}