
[
 {
  "Number" : 0,
  "Name"   : "Show Timothy around the house",
  "Hidden" : false,
  "Weekly" : true,
  "ShowAll" : false,
  "GoalAll" : true,
  "FailAll" : false,
  "SubCount" : 5,
  "SubTasks" : [
   {
    "Number" : 0,
    "Name"   : "Show Timothy the Cafe",
    "Hidden" : false
   },
   {
    "Number" : 1,
    "Name"   : "Show Timothy the Commons",
    "Hidden" : false
   },
   {
    "Number" : 2,
    "Name"   : "Show Timothy the Gardens",
    "Hidden" : false
   },
   {
    "Number" : 3,
    "Name"   : "Show Timothy the Art Room",
    "Hidden" : false
   },
   {
    "Number" : 4,
    "Name"   : "Show Timothy the Library",
    "Hidden" : false
   }
  ]
 },
 {
  "Number" : 1,
  "Name"   : "Go to Timothy's Welcome Dinner",
  "Hidden" : false,
  "Weekly" : true,
  "ShowAll" : false,
  "GoalAll" : false,
  "FailAll" : false,
  "SubCount" : 0,
  "SubTasks" : [
  ]
 },
 {
  "Number" : 2,
  "Name"   : "Hangout with Isaac before Friday",
  "Hidden" : false,
  "Weekly" : false,
  "ShowAll" : false,
  "GoalAll" : false,
  "FailAll" : false,
  "SubCount" : 0,
  "SubTasks" : [
  ]
 },
 {
  "Number" : 3,
  "Name"   : "Find Eduardo & Isaac Late Tuesday Night",
  "Hidden" : false,
  "Weekly" : false,
  "ShowAll" : false,
  "GoalAll" : false,
  "FailAll" : false,
  "SubCount" : 0,
  "SubTasks" : [
  ]
 },
 {
  "Number" : 4,
  "Name"   : "Talk to Isaac Alone",
  "Hidden" : false,
  "Weekly" : false,
  "ShowAll" : false,
  "GoalAll" : false,
  "FailAll" : false,
  "SubCount" : 0,
  "SubTasks" : [
  ]
 },
 {
  "Number" : 5,
  "Name"   : "Get a key for your bedroom",
  "Hidden" : false,
  "Weekly" : false,
  "ShowAll" : false,
  "GoalAll" : false,
  "FailAll" : false,
  "SubCount" : 0,
  "SubTasks" : [
  ]
 },
 {
  "Number" : 6,
  "Name"   : "Convince Eduardo on Thursday Morning",
  "Hidden" : false,
  "Weekly" : false,
  "ShowAll" : false,
  "GoalAll" : false,
  "FailAll" : false,
  "SubCount" : 0,
  "SubTasks" : [
  ]
 },
 {
  "Number" : 7,
  "Name"   : "Help Timoth dye his hair",
  "Hidden" : false,
  "Weekly" : true,
  "ShowAll" : false,
  "GoalAll" : false,
  "FailAll" : false,
  "SubCount" : 2,
  "SubTasks" : [
   {
    "Number" : 0,
    "Name"   : "Find Eduardo's hair dye",
    "Hidden" : false
   },
   {
    "Number" : 1,
    "Name"   : "Find proof for Max",
    "Hidden" : false
   }
  ]
 }
]